cybotrade_datasource-0.1.9.dist-info/METADATA
cybotrade_datasource-0.1.9.dist-info/WHEEL
cybotrade_datasource-0.1.9.dist-info/licenses/LICENSE
cybotrade_datasource/__init__.py
cybotrade_datasource/cybotrade_datasource.cpython-314-darwin.so
cybotrade_datasource/cybotrade_datasource.pyi
cybotrade_datasource/py.typed
cybotrade_datasource-0.1.9.dist-info/RECORD
