Metadata-Version: 2.4
Name: cybotrade-datasource
Version: 0.1.9
Classifier: Programming Language :: Rust
Classifier: Programming Language :: Python :: Implementation :: CPython
Classifier: Programming Language :: Python :: Implementation :: PyPy
License-File: LICENSE
Summary: Python SDK to interact with Cybotrade Datasource API.
Author-email: Marcus Lee <marcuslee@balaenaquant.com>, Lee Ian <ianlee@balaenaquant.com>
Requires-Python: >=3.12
Project-URL: Documentation, https://docs.datasource.cybotrade.rs
